[
    {
        "name": "/echo",
        "method": "GET",
        "last_request_timestamp": 1773697864.0408058,
        "start_time": 1773697806.979063,
        "num_requests": 106771,
        "num_none_requests": 0,
        "num_failures": 0,
        "total_response_time": 13832779.225075845,
        "max_response_time": 372.3921939963475,
        "min_response_time": 3.374736988916993,
        "total_content_length": 2242191,
        "response_times": {
            "13": 2,
            "6": 3,
            "7": 8,
            "9": 2,
            "11": 4,
            "14": 5,
            "97": 858,
            "42": 19,
            "64": 271,
            "110.0": 5957,
            "68": 997,
            "57": 106,
            "44": 3,
            "120.0": 2241,
            "55": 85,
            "43": 11,
            "56": 64,
            "240.0": 56,
            "210.0": 1035,
            "85": 1320,
            "160.0": 8820,
            "45": 2,
            "130.0": 963,
            "94": 1474,
            "150.0": 6775,
            "83": 990,
            "88": 1732,
            "140.0": 2098,
            "87": 1656,
            "12": 1,
            "5": 5,
            "8": 6,
            "10": 2,
            "90": 1316,
            "38": 22,
            "48": 12,
            "61": 139,
            "39": 26,
            "60": 175,
            "230.0": 174,
            "86": 1319,
            "170.0": 9880,
            "73": 1103,
            "91": 1516,
            "100.0": 3962,
            "190.0": 7538,
            "67": 931,
            "200.0": 3403,
            "80": 702,
            "50": 43,
            "75": 1131,
            "77": 1080,
            "58": 154,
            "46": 5,
            "53": 47,
            "41": 15,
            "51": 18,
            "40": 8,
            "54": 45,
            "63": 330,
            "260.0": 9,
            "360.0": 1,
            "220.0": 564,
            "250.0": 21,
            "36": 16,
            "4": 5,
            "47": 11,
            "62": 304,
            "370.0": 1,
            "84": 1129,
            "180.0": 11386,
            "59": 181,
            "74": 1471,
            "300.0": 3,
            "21": 1,
            "29": 3,
            "49": 28,
            "93": 1487,
            "79": 878,
            "65": 471,
            "3": 1,
            "92": 1544,
            "16": 1,
            "15": 1,
            "99": 740,
            "89": 1566,
            "95": 1390,
            "96": 1034,
            "81": 794,
            "69": 1012,
            "35": 3,
            "66": 655,
            "76": 946,
            "70": 1214,
            "82": 867,
            "98": 849,
            "72": 1273,
            "71": 1269,
            "78": 910,
            "320.0": 1,
            "270.0": 3,
            "33": 3,
            "37": 24,
            "52": 28,
            "25": 2,
            "30": 2,
            "22": 1,
            "17": 1,
            "24": 1,
            "31": 1
        },
        "num_reqs_per_sec": {
            "1773697806": 7,
            "1773697807": 87,
            "1773697808": 83,
            "1773697809": 89,
            "1773697810": 1694,
            "1773697811": 1990,
            "1773697812": 2023,
            "1773697813": 1982,
            "1773697814": 2027,
            "1773697815": 1990,
            "1773697816": 2022,
            "1773697817": 1877,
            "1773697818": 2129,
            "1773697819": 1971,
            "1773697820": 1868,
            "1773697821": 2123,
            "1773697822": 1944,
            "1773697823": 2029,
            "1773697824": 2051,
            "1773697825": 1944,
            "1773697826": 1792,
            "1773697827": 2023,
            "1773697828": 2018,
            "1773697829": 1767,
            "1773697830": 1997,
            "1773697831": 1978,
            "1773697832": 1976,
            "1773697833": 1928,
            "1773697834": 1998,
            "1773697835": 2000,
            "1773697836": 1856,
            "1773697837": 1977,
            "1773697838": 2005,
            "1773697839": 2044,
            "1773697840": 1995,
            "1773697841": 1795,
            "1773697842": 1958,
            "1773697843": 2019,
            "1773697844": 2025,
            "1773697845": 1985,
            "1773697846": 1899,
            "1773697847": 1919,
            "1773697848": 2139,
            "1773697849": 1968,
            "1773697850": 1895,
            "1773697851": 1890,
            "1773697852": 2079,
            "1773697853": 2049,
            "1773697854": 1897,
            "1773697855": 1852,
            "1773697856": 2010,
            "1773697857": 2207,
            "1773697858": 1838,
            "1773697859": 1990,
            "1773697860": 1934,
            "1773697861": 2009,
            "1773697862": 2082,
            "1773697863": 1915,
            "1773697864": 133
        },
        "num_fail_per_sec": {}
    }
]